Metadata-Version: 2.4
Name: make4db-duckdb
Version: 0.1.2
Summary: make4db provider for DuckDB
Author-email: Paresh Adhia <padhia+github@gmail.com>
Classifier: Programming Language :: Python :: 3
Requires-Python: >=3.11
Requires-Dist: make4db-api
Requires-Dist: duckdb
